scrippy_core/__init__.py
scrippy_core/arguments/__init__.py
scrippy_core/arguments/historyaction.py
scrippy_core/arguments/logaction.py
scrippy_core/arguments/sourceaction.py
scrippy_core/conf/__init__.py
scrippy_core/context/__init__.py
scrippy_core/error_handler/__init__.py
scrippy_core/history/__init__.py
scrippy_core/logger/__init__.py
scrippy_core/logger/manager/__init__.py
scrippy_core/scriptinfo/__init__.py
scrippy_core/stack/__init__.py
scrippy_core/vault/__init__.py
scrippy_core/workspace/__init__.py
scrippy_core-2.0.4.dist-info/LICENSE
scrippy_core-2.0.4.dist-info/METADATA
scrippy_core-2.0.4.dist-info/WHEEL
scrippy_core-2.0.4.dist-info/top_level.txt
scrippy_core-2.0.4.dist-info/RECORD
